LICENSE
MANIFEST.in
Readme.md
setup.py
layoutx/__init__.py
layoutx/_parser.py
layoutx/_registry.py
layoutx/app.py
layoutx/install_tkdnd.py
layoutx/store.py
layoutx/utils.py
layoutx/view.py
layoutx.egg-info/PKG-INFO
layoutx.egg-info/SOURCES.txt
layoutx.egg-info/dependency_links.txt
layoutx.egg-info/entry_points.txt
layoutx.egg-info/requires.txt
layoutx.egg-info/top_level.txt
layoutx/resources/favicon.ico
layoutx/tkDnD/TkinterDnD.py
layoutx/tkDnD/__init__.py
layoutx/tools/__init__.py
layoutx/tools/designer.py
layoutx/widgets/__init__.py
layoutx/widgets/box.py
layoutx/widgets/button.py
layoutx/widgets/checkbox.py
layoutx/widgets/combobox.py
layoutx/widgets/drop_target.py
layoutx/widgets/formitem.py
layoutx/widgets/input.py
layoutx/widgets/label.py
layoutx/widgets/listbox.py
layoutx/widgets/logger.py
layoutx/widgets/notebook.py
layoutx/widgets/scale.py
layoutx/widgets/scroll_frame.py
layoutx/widgets/seperator.py
layoutx/widgets/splitpane.py
layoutx/widgets/textarea.py
layoutx/widgets/widget.py