Metadata-Version: 2.1
Name: layoutx
Version: 1.2
Summary: Declarative tkinter layout engine with reactive data binding
Home-page: https://github.com/Bomberus/LayoutX
Author: Pascal Maximilian Bremer
License: UNKNOWN
Platform: UNKNOWN
Classifier: Development Status :: 3 - Alpha
Classifier: Intended Audience :: Developers
Classifier: License :: OSI Approved :: MIT License
Classifier: Programming Language :: Python :: 3.8
Classifier: Programming Language :: Python :: 3.7
Classifier: Topic :: Software Development
Provides-Extra: more_widgets
Provides-Extra: styles
